Workbook
Name Sales_Date: OFFSET('RAW_Sales Data'!$A$1,0,0, COUNT('RAW_Sales Data'!$A:$A),COUNTA('RAW_Sales Data'!$1:$1))
Name Slicer_Product_Name: #N/A
Name Slicer_Sales_Manager: #N/A
Name Slicer_Year1: #N/A

Sheet Project_Overview

Sheet Dashboard
B12: Filter | E12: Revenue by Quarter Forecast | S12: Revenue by Year
E32: Revenue by Country | P32: Revenue by Year Forecast

Sheet Manager_Lookup
B2: What is the total revenue and total profit generated by the selected Sales Manager?
B3: Sales Manager | C3: Total Revenue | D3: Total Profit | E3: Profit Margin | F3: Ranking
B4: John Smith | C4: =_xlfn.XLOOKUP(B4,Pivot_Tables!C38:C42,Pivot_Tables!D38:D42,"Not Found") -> 42195150 | D4: =_xlfn.XLOOKUP(B4,Pivot_Tables!C38:C42,Pivot_Tables!E38:E42,"Not Found") -> 11307144 | E4: =D4/C4 -> 0.26797261 | F4: =RANK(C4,Pivot_Tables!D38:D42,0) -> 1

Sheet Calculations
A1: Total Revenue | C1: Total Revenue by Region | I1: Revenue Growth by year | N1: Total Profit By Year
A2: =SUM(Cleaned_Sales_Data!J:J) -> 198520850 | C2: Canada | D2: New Zealand | E2: UK | F2: Australia | G2: USA | I2: 2019 | J2: 2020 | K2: 2021 | L2: 2022 | N2: 2019 | O2: 2020 | P2: 2021 | Q2: 2022
C3: =SUMIFS(Sales_Data[Sales Amount],Sales_Data[Country],"Canada") -> 40570250 | D3: =SUMIFS(Sales_Data[Sales Amount],Sales_Data[Country],"New Zealand") -> 42704700 | E3: =SUMIFS(Sales_Data[Sales Amount],Sales_Data[Country],"UK") -> 36261800 | F3: =SUMIFS(Sales_Data[Sales Amount],Sales_Data[Country],"Australia") -> 39320800 | G3: =SUMIFS(Sales_Data[Sales Amount],Sales_Data[Country],"USA") -> 39663300 | I3: =SUM(Cleaned_Sales_Data!J2:J366) -> 50449050 | J3: =SUM(Cleaned_Sales_Data!J367:J732) -> 48060500 | K3: =SUM(Cleaned_Sales_Data!J733:J1097) -> 50464650 | L3: =SUM(Cleaned_Sales_Data!J1098:J1462) -> 49546650 | N3: =SUMIFS(Sales_Data[Total Profit], Sales_Data[Year],2019) -> 14200362 | O3: =SUMIFS(Sales_Data[Total Profit], Sales_Data[Year],2020) -> 12946366 | P3: =SUMIFS(Sales_Data[Total Profit], Sales_Data[Year],2021) -> 13187944 | Q3: =SUMIFS(Sales_Data[Total Profit], Sales_Data[Year],2022) -> 13557558
A4: Total Profit | J4: =(J3-I3)/I3 -> -0.047345787 | K4: =(K3-J3)/J3 -> 0.050023408 | L4: =(L3-K3)/K3 -> -0.018190951
A5: =SUM(Cleaned_Sales_Data!K:K) -> 53892229 | C5: Number of profitable orders > 100,000€ | F5: Total number of profitable orders
C6: =COUNTIFS(Sales_Data[Total Profit], ">100000") -> 83 | F6: =COUNTIFS(Sales_Data[Profitable_Flag],"Profitable") -> 1461
A7: Total Orders
A8: =COUNTA(Sales_Data[Order ID]) -> 1461
A10: Average Order Value | D10: 2022 Total Revenue | F10: 2022 Total Profit | I10: 2022 Total Margin profit %
A11: =A2/A8 -> 135880.12 | D11: =SUM(Cleaned_Sales_Data!J1098:J1462) -> 49546650 | F11: =SUM(Cleaned_Sales_Data!K1098:K1462) -> 13557558 | I11: =Q3/L3 -> 0.27363217
D13: 2022 Total orders
D14: =COUNTIF(Sales_Data[[#All],[Year]],"2022") -> 365

Sheet Pivot_Tables
B1: Total Revenue | E1: Region with highest performance | I1: Highest product profits | L1: 2022 Monthly revenue trend
C2: Total_Revenue | E2: Region | F2: Total_Revenue | I2: Product | J2: Total_Profit | L2: 2022 Month | M2: Total_Revenue
C3: 198520850 | E3: New Zealand | F3: 0.21511443 | I3: Product D | J3: 16134300 | L3: jan | M3: 5110500
E4: Canada | F4: 0.20436267 | I4: Product E | J4: 14778292 | L4: fev | M4: 3392600
E5: USA | F5: 0.19979413 | I5: Product A | J5: 10219915 | L5: mar | M5: 4517900
E6: Australia | F6: 0.19806887 | I6: Product C | J6: 7564886 | L6: abr | M6: 4032500
E7: UK | F7: 0.18265991 | I7: Product B | J7: 5194835 | L7: mai | M7: 4229600
E8: Grand Total | F8: 1 | I8: Grand Total | J8: 53892229 | L8: jun | M8: 3563950
L9: jul | M9: 3904750
C10: YoY Growth | L10: ago | M10: 4321450
C11: Row Labels | D11: Total_Revenue | E11: YoY % Growth | L11: set | M11: 3471850
C12: 2019 | D12: 50449050 | L12: out | M12: 4496100
C13: 2020 | D13: 48060500 | E13: =(GETPIVOTDATA("Sales Amount",$C$11,"Year",2020)-GETPIVOTDATA("Sales Amount",$C$11,"Year",2019))/GETPIVOTDATA("Sales Amount",$C$11,"Year",2019) -> -0.047345787 | L13: nov | M13: 4134800
C14: 2021 | D14: 50464650 | E14: =(GETPIVOTDATA("Sales Amount",$C$11,"Year",2021)-GETPIVOTDATA("Sales Amount",$C$11,"Year",2020))/GETPIVOTDATA("Sales Amount",$C$11,"Year",2020) -> 0.050023408 | L14: dez | M14: 4370650
C15: 2022 | D15: 49546650 | E15: =(GETPIVOTDATA("Sales Amount",$C$11,"Year",2022)-GETPIVOTDATA("Sales Amount",$C$11,"Year",2021))/GETPIVOTDATA("Sales Amount",$C$11,"Year",2021) -> -0.018190951 | L15: Grand Total | M15: 49546650
C16: Grand Total | D16: 198520850
C18: Margin | L18: Row Labels | M18: Sum of Sales Amount | N18: Sales_%
C19: Product | D19: Total_Revenue | E19: Total_Profit | F19: Margin | L19: 2019 | M19: 50449050 | N19: 0.25412469
C20: Product A | D20: 37810000 | E20: 10219915 | F20: {=E20:E24/D20:D24} -> 0.27029661 | L20: 2020 | M20: 48060500 | N20: 0.24209296
C21: Product B | D21: 18683000 | E21: 5194835 | F21: 0.27805144 | L21: 2021 | M21: 50464650 | N21: 0.25420327
C22: Product C | D22: 28120750 | E22: 7564886 | F22: 0.26901438 | L22: 2022 | M22: 49546650 | N22: 0.24957907
C23: Product D | D23: 58268350 | E23: 16134300 | F23: 0.27689647 | L23: Grand Total | M23: 198520850 | N23: 1
C24: Product E | D24: 55638750 | E24: 14778292 | F24: 0.26561151
C25: Grand Total | D25: 198520850 | E25: 53892229
L27: Row Labels | M27: Sales_% | O27: Row Labels | P27: Sales_%
C28: Row Labels | D28: Sum of Sales Amount | L28: Australia | M28: 0.19806887 | O28: Emily White | P28: 0.20279986
C29: Emily White | D29: 40260000 | L29: Canada | M29: 0.20436267 | O29: James Brown | P29: 0.19462515
C30: James Brown | D30: 38637150 | L30: New Zealand | M30: 0.21511443 | O30: Jane Doe | P30: 0.20003088
C31: Jane Doe | D31: 39710300 | L31: UK | M31: 0.18265991 | O31: John Smith | P31: 0.2125477
C32: John Smith | D32: 42195150 | L32: USA | M32: 0.19979413 | O32: Liam Lee | P32: 0.18999642
C33: Liam Lee | D33: 37718250 | L33: Grand Total | M33: 1 | O33: Grand Total | P33: 1
C34: Grand Total | D34: 198520850
C37: Row Labels | D37: Total_Sales_Amount | E37: Total_ Profit
C38: Emily White | D38: 40260000 | E38: 10874170
C39: James Brown | D39: 38637150 | E39: 10121145
C40: Jane Doe | D40: 39710300 | E40: 11268737
C41: John Smith | D41: 42195150 | E41: 11307144
C42: Liam Lee | D42: 37718250 | E42: 10321033
C43: Grand Total | D43: 198520850 | E43: 53892229

Sheet Forecast_yearly
A1: YoY Growth | B1: Values | C1: Forecast | D1: Lower Confidence Bound | E1: Upper Confidence Bound
A2: 2019 | B2: 50449050
A3: 2020 | B3: 48060500
A4: 2021 | B4: 50464650
A5: 2022 | B5: 49546650 | C5: 49546650 | D5: 49546650 | E5: 49546650
A6: 2023 | C6: =_xlfn.FORECAST.ETS(A6,$B$2:$B$5,$A$2:$A$5,1,1) -> 49503850 | D6: =C6-_xlfn.FORECAST.ETS.CONFINT(A6,$B$2:$B$5,$A$2:$A$5,0.95,1,1) -> 47124307 | E6: =C6+_xlfn.FORECAST.ETS.CONFINT(A6,$B$2:$B$5,$A$2:$A$5,0.95,1,1) -> 51883394

Sheet Forecast_Revenue_Quarter
A1: Start of Quarter | B1: Sales Amount | C1: Forecast( Sales Amount ) | D1: Lower Confidence Bound( Sales Amount ) | E1: Upper Confidence Bound( Sales Amount )
A2: 43466 | B2: 128288.33
A3: 43556 | B3: 156161.54
A4: 43647 | B4: 138032.07
A5: 43739 | B5: 130363.59
A6: 43831 | B6: 114774.73
A7: 43922 | B7: 144482.97
A8: 44013 | B8: 136421.74
A9: 44105 | B9: 129535.33
A10: 44197 | B10: 136283.33
A11: 44287 | B11: 147620.33
A12: 44378 | B12: 138054.89
A13: 44470 | B13: 131137.5
... A16: 44743 | B16: 127152.72
A17: 44835 | B17: 141321.2 | C17: 141321.2 | D17: 141321.2 | E17: 141321.2
A18: 44927 | C18: =_xlfn.FORECAST.ETS(A18,$B$2:$B$17,$A$2:$A$17,2,1) -> 129648.75 | D18: =C18-_xlfn.FORECAST.ETS.CONFINT(A18,$B$2:$B$17,$A$2:$A$17,0.95,2,1) -> 109851.71 | E18: =C18+_xlfn.FORECAST.ETS.CONFINT(A18,$B$2:$B$17,$A$2:$A$17,0.95,2,1) -> 149445.8
A19: 45017 | C19: =_xlfn.FORECAST.ETS(A19,$B$2:$B$17,$A$2:$A$17,2,1) -> 137894.83 | D19: =C19-_xlfn.FORECAST.ETS.CONFINT(A19,$B$2:$B$17,$A$2:$A$17,0.95,2,1) -> 118097.69 | E19: =C19+_xlfn.FORECAST.ETS.CONFINT(A19,$B$2:$B$17,$A$2:$A$17,0.95,2,1) -> 157691.96
A20: 45108 | C20: =_xlfn.FORECAST.ETS(A20,$B$2:$B$17,$A$2:$A$17,2,1) -> 129241.85 | D20: =C20-_xlfn.FORECAST.ETS.CONFINT(A20,$B$2:$B$17,$A$2:$A$17,0.95,2,1) -> 109280.67 | E20: =C20+_xlfn.FORECAST.ETS.CONFINT(A20,$B$2:$B$17,$A$2:$A$17,0.95,2,1) -> 149203.02
A21: 45200 | C21: =_xlfn.FORECAST.ETS(A21,$B$2:$B$17,$A$2:$A$17,2,1) -> 137487.92 | D21: =C21-_xlfn.FORECAST.ETS.CONFINT(A21,$B$2:$B$17,$A$2:$A$17,0.95,2,1) -> 117526.5 | E21: =C21+_xlfn.FORECAST.ETS.CONFINT(A21,$B$2:$B$17,$A$2:$A$17,0.95,2,1) -> 157449.34

Sheet Cleaned_Sales_Data
A1: Order ID | B1: Year | C1: Month Name | D1: Date | E1: Country | F1: Sales Manager | G1: Product Name | H1: Total Transations | I1: Quantity Sold | J1: Sales Amount | K1: Total Profit | L1: Week of Year | M1: Start of Quarter | N1: Sales_amount_% | O1: Profitable_Flag | P1: Profit_Value_Flag | Q1: Month_name_clean | R1: Manager_clean
A2: 10001 | B2: 2019 | C2: janeiro | D2: 43466 | E2: USA | F2: Emily White | G2: Product E | H2: 34 | I2: 348 | J2: 261000 | K2: 60030 | L2: 1 | M2: 43466 | N2: 0.0013147234 | O2: =IF(Sales_Data[[#This Row],[Total Profit]]>0,"Profitable","Loss") -> Profitable | P2: =IF(Sales_Data[[#This Row],[Total Profit]]>100000,"High Value",IF(Sales_Data[[#This Row],[Total Profit]]>60000,"Medium","Low")) -> Medium | Q2: =PROPER(Sales_Data[[#This Row],[Month Name]]) -> Janeiro | R2: =PROPER(Sales_Data[[#This Row],[Sales Manager]]) -> Emily White
A3: 10002 | B3: 2019 | C3: janeiro | D3: 43467 | E3: Canada | F3: Emily White | G3: Product A | H3: 4 | I3: 145 | J3: 72500 | K3: 13775 | L3: 1 | M3: 43466 | N3: 0.00036520093 | O3: =IF(Sales_Data[[#This Row],[Total Profit]]>0,"Profitable","Loss") -> Profitable | P3: =IF(Sales_Data[[#This Row],[Total Profit]]>100000,"High Value",IF(Sales_Data[[#This Row],[Total Profit]]>60000,"Medium","Low")) -> Low | Q3: =PROPER(Sales_Data[[#This Row],[Month Name]]) -> Janeiro | R3: =PROPER(Sales_Data[[#This Row],[Sales Manager]]) -> Emily White
A4: 10003 | B4: 2019 | C4: janeiro | D4: 43468 | E4: Canada | F4: James Brown | G4: Product B | H4: 11 | I4: 427 | J4: 106750 | K4: 40565 | L4: 1 | M4: 43466 | N4: 0.00053772689 | O4: =IF(Sales_Data[[#This Row],[Total Profit]]>0,"Profitable","Loss") -> Profitable | P4: =IF(Sales_Data[[#This Row],[Total Profit]]>100000,"High Value",IF(Sales_Data[[#This Row],[Total Profit]]>60000,"Medium","Low")) -> Low | Q4: =PROPER(Sales_Data[[#This Row],[Month Name]]) -> Janeiro | R4: =PROPER(Sales_Data[[#This Row],[Sales Manager]]) -> James Brown
A5: 10004 | B5: 2019 | C5: janeiro | D5: 43469 | E5: USA | F5: Emily White | G5: Product E | H5: 16 | I5: 388 | J5: 291000 | K5: 110580 | L5: 1 | M5: 43466 | N5: 0.001465841 | O5: =IF(Sales_Data[[#This Row],[Total Profit]]>0,"Profitable","Loss") -> Profitable | P5: =IF(Sales_Data[[#This Row],[Total Profit]]>100000,"High Value",IF(Sales_Data[[#This Row],[Total Profit]]>60000,"Medium","Low")) -> High Value | Q5: =PROPER(Sales_Data[[#This Row],[Month Name]]) -> Janeiro | R5: =PROPER(Sales_Data[[#This Row],[Sales Manager]]) -> Emily White
A6: 10005 | B6: 2019 | C6: janeiro | D6: 43470 | E6: Canada | F6: Jane Doe | G6: Product A | H6: 34 | I6: 363 | J6: 181500 | K6: 39930 | L6: 1 | M6: 43466 | N6: 0.00091426165 | O6: =IF(Sales_Data[[#This Row],[Total Profit]]>0,"Profitable","Loss") -> Profitable | P6: =IF(Sales_Data[[#This Row],[Total Profit]]>100000,"High Value",IF(Sales_Data[[#This Row],[Total Profit]]>60000,"Medium","Low")) -> Low | Q6: =PROPER(Sales_Data[[#This Row],[Month Name]]) -> Janeiro | R6: =PROPER(Sales_Data[[#This Row],[Sales Manager]]) -> Jane Doe
A7: 10006 | B7: 2019 | C7: janeiro | D7: 43471 | E7: Australia | F7: James Brown | G7: Product D | H7: 5 | I7: 124 | J7: 105400 | K7: 37944 | L7: 2 | M7: 43466 | N7: 0.0005309266 | O7: =IF(Sales_Data[[#This Row],[Total Profit]]>0,"Profitable","Loss") -> Profitable | P7: =IF(Sales_Data[[#This Row],[Total Profit]]>100000,"High Value",IF(Sales_Data[[#This Row],[Total Profit]]>60000,"Medium","Low")) -> Low | Q7: =PROPER(Sales_Data[[#This Row],[Month Name]]) -> Janeiro | R7: =PROPER(Sales_Data[[#This Row],[Sales Manager]]) -> James Brown
A8: 10007 | B8: 2019 | C8: janeiro | D8: 43472 | E8: Canada | F8: John Smith | G8: Product B | H8: 13 | I8: 389 | J8: 97250 | K8: 41817.5 | L8: 2 | M8: 43466 | N8: 0.00048987298 | O8: =IF(Sales_Data[[#This Row],[Total Profit]]>0,"Profitable","Loss") -> Profitable | P8: =IF(Sales_Data[[#This Row],[Total Profit]]>100000,"High Value",IF(Sales_Data[[#This Row],[Total Profit]]>60000,"Medium","Low")) -> Low | Q8: =PROPER(Sales_Data[[#This Row],[Month Name]]) -> Janeiro | R8: =PROPER(Sales_Data[[#This Row],[Sales Manager]]) -> John Smith
A9: 10008 | B9: 2019 | C9: janeiro | D9: 43473 | E9: Canada | F9: Jane Doe | G9: Product A | H9: 3 | I9: 132 | J9: 66000 | K9: 23100 | L9: 2 | M9: 43466 | N9: 0.00033245878 | O9: =IF(Sales_Data[[#This Row],[Total Profit]]>0,"Profitable","Loss") -> Profitable | P9: =IF(Sales_Data[[#This Row],[Total Profit]]>100000,"High Value",IF(Sales_Data[[#This Row],[Total Profit]]>60000,"Medium","Low")) -> Low | Q9: =PROPER(Sales_Data[[#This Row],[Month Name]]) -> Janeiro | R9: =PROPER(Sales_Data[[#This Row],[Sales Manager]]) -> Jane Doe
A10: 10009 | B10: 2019 | C10: janeiro | D10: 43474 | E10: New Zealand | F10: Emily White | G10: Product C | H10: 4 | I10: 58 | J10: 20300 | K10: 7917 | L10: 2 | M10: 43466 | N10: 0.00010225626 | O10: =IF(Sales_Data[[#This Row],[Total Profit]]>0,"Profitable","Loss") -> Profitable | P10: =IF(Sales_Data[[#This Row],[Total Profit]]>100000,"High Value",IF(Sales_Data[[#This Row],[Total Profit]]>60000,"Medium","Low")) -> Low | Q10: =PROPER(Sales_Data[[#This Row],[Month Name]]) -> Janeiro | R10: =PROPER(Sales_Data[[#This Row],[Sales Manager]]) -> Emily White
A11: 10010 | B11: 2019 | C11: janeiro | D11: 43475 | E11: Australia | F11: Liam Lee | G11: Product E | H11: 25 | I11: 261 | J11: 195750 | K11: 27405 | L11: 2 | M11: 43466 | N11: 0.00098604252 | O11: =IF(Sales_Data[[#This Row],[Total Profit]]>0,"Profitable","Loss") -> Profitable | P11: =IF(Sales_Data[[#This Row],[Total Profit]]>100000,"High Value",IF(Sales_Data[[#This Row],[Total Profit]]>60000,"Medium","Low")) -> Low | Q11: =PROPER(Sales_Data[[#This Row],[Month Name]]) -> Janeiro | R11: =PROPER(Sales_Data[[#This Row],[Sales Manager]]) -> Liam Lee
A12: 10011 | B12: 2019 | C12: janeiro | D12: 43476 | E12: Canada | F12: Jane Doe | G12: Product E | H12: 17 | I12: 275 | J12: 206250 | K12: 72187.5 | L12: 2 | M12: 43466 | N12: 0.0010389337 | O12: =IF(Sales_Data[[#This Row],[Total Profit]]>0,"Profitable","Loss") -> Profitable | P12: =IF(Sales_Data[[#This Row],[Total Profit]]>100000,"High Value",IF(Sales_Data[[#This Row],[Total Profit]]>60000,"Medium","Low")) -> Medium | Q12: =PROPER(Sales_Data[[#This Row],[Month Name]]) -> Janeiro | R12: =PROPER(Sales_Data[[#This Row],[Sales Manager]]) -> Jane Doe
A13: 10012 | B13: 2019 | C13: janeiro | D13: 43477 | E13: USA | F13: James Brown | G13: Product D | H13: 7 | I13: 348 | J13: 295800 | K13: 68034 | L13: 2 | M13: 43466 | N13: 0.0014900198 | O13: =IF(Sales_Data[[#This Row],[Total Profit]]>0,"Profitable","Loss") -> Profitable | P13: =IF(Sales_Data[[#This Row],[Total Profit]]>100000,"High Value",IF(Sales_Data[[#This Row],[Total Profit]]>60000,"Medium","Low")) -> Medium | Q13: =PROPER(Sales_Data[[#This Row],[Month Name]]) -> Janeiro | R13: =PROPER(Sales_Data[[#This Row],[Sales Manager]]) -> James Brown
... A1462: 11461 | B1462: 2022 | C1462: dezembro | D1462: 44926 | E1462: Canada | F1462: Emily White | G1462: Product D | H1462: 1 | I1462: 50 | J1462: 42500 | K1462: 18275 | L1462: 53 | M1462: 44835 | N1462: 0.00021408331 | O1462: =IF(Sales_Data[[#This Row],[Total Profit]]>0,"Profitable","Loss") -> Profitable | P1462: =IF(Sales_Data[[#This Row],[Total Profit]]>100000,"High Value",IF(Sales_Data[[#This Row],[Total Profit]]>60000,"Medium","Low")) -> Low | Q1462: =PROPER(Sales_Data[[#This Row],[Month Name]]) -> Dezembro | R1462: =PROPER(Sales_Data[[#This Row],[Sales Manager]]) -> Emily White

Sheet RAW_Sales Data
A1: Order ID | B1: Year | C1: Month | D1: Date | E1: Country | F1: Sales Manager | G1: Product Name | H1: Total Transations | I1: Quantity Sold | J1: Sales Amount | K1: Total Profit
A2: 10001 | B2: =YEAR(C2) -> 2019 | C2: 43466 | D2: 43466 | E2: USA | F2: Emily White | G2: Product E | H2: 34 | I2: 348 | J2: 261000 | K2: 60030
A3: 10002 | B3: =YEAR(C3) -> 2019 | C3: 43466 | D3: 43467 | E3: Canada | F3: Emily White | G3: Product A | H3: 4 | I3: 145 | J3: 72500 | K3: 13775
A4: 10003 | B4: =YEAR(C4) -> 2019 | C4: 43466 | D4: 43468 | E4: Canada | F4: James Brown | G4: Product B | H4: 11 | I4: 427 | J4: 106750 | K4: 40565
A5: 10004 | B5: =YEAR(C5) -> 2019 | C5: 43466 | D5: 43469 | E5: USA | F5: Emily White | G5: Product E | H5: 16 | I5: 388 | J5: 291000 | K5: 110580
A6: 10005 | B6: =YEAR(C6) -> 2019 | C6: 43466 | D6: 43470 | E6: Canada | F6: Jane Doe | G6: Product A | H6: 34 | I6: 363 | J6: 181500 | K6: 39930
A7: 10006 | B7: =YEAR(C7) -> 2019 | C7: 43466 | D7: 43471 | E7: Australia | F7: James Brown | G7: Product D | H7: 5 | I7: 124 | J7: 105400 | K7: 37944
A8: 10007 | B8: =YEAR(C8) -> 2019 | C8: 43466 | D8: 43472 | E8: Canada | F8: John Smith | G8: Product B | H8: 13 | I8: 389 | J8: 97250 | K8: 41817.5
A9: 10008 | B9: =YEAR(C9) -> 2019 | C9: 43466 | D9: 43473 | E9: Canada | F9: Jane Doe | G9: Product A | H9: 3 | I9: 132 | J9: 66000 | K9: 23100
A10: 10009 | B10: =YEAR(C10) -> 2019 | C10: 43466 | D10: 43474 | E10: New Zealand | F10: Emily White | G10: Product C | H10: 4 | I10: 58 | J10: 20300 | K10: 7917
A11: 10010 | B11: =YEAR(C11) -> 2019 | C11: 43466 | D11: 43475 | E11: Australia | F11: Liam Lee | G11: Product E | H11: 25 | I11: 261 | J11: 195750 | K11: 27405
A12: 10011 | B12: =YEAR(C12) -> 2019 | C12: 43466 | D12: 43476 | E12: Canada | F12: Jane Doe | G12: Product E | H12: 17 | I12: 275 | J12: 206250 | K12: 72187.5
A13: 10012 | B13: =YEAR(C13) -> 2019 | C13: 43466 | D13: 43477 | E13: USA | F13: James Brown | G13: Product D | H13: 7 | I13: 348 | J13: 295800 | K13: 68034
... A1235: 11234 | B1235: =YEAR(C1235) -> 2022 | C1235: 44682 | D1235: 44699 | E1235: Canada | F1235: Emily White | G1235: Product E | H1235: 27 | I1235: 402 | J1235: 301500 | K1235: 132660
A1236: 11235 | B1236: =YEAR(C1236) -> 2022 | C1236: 44682 | D1236: =D1235+1 -> 44700 | E1236: UK | F1236: Jane Doe | G1236: Product D | H1236: 32 | I1236: 396 | J1236: 336600 | K1236: 144738
A1237: 11236 | B1237: =YEAR(C1237) -> 2022 | C1237: 44682 | D1237: =D1236+1 -> 44701 | E1237: Australia | F1237: Emily White | G1237: Product C | H1237: 18 | I1237: 409 | J1237: 143150 | K1237: 47239.5
A1238: 11237 | B1238: =YEAR(C1238) -> 2022 | C1238: 44682 | D1238: =D1237+1 -> 44702 | E1238: USA | F1238: Emily White | G1238: Product D | H1238: 2 | I1238: 44 | J1238: 37400 | K1238: 12716
A1239: 11238 | B1239: =YEAR(C1239) -> 2022 | C1239: 44682 | D1239: =D1238+1 -> 44703 | E1239: USA | F1239: Liam Lee | G1239: Product A | H1239: 31 | I1239: 467 | J1239: 233500 | K1239: 86395
A1240: 11239 | B1240: =YEAR(C1240) -> 2022 | C1240: 44682 | D1240: =D1239+1 -> 44704 | E1240: Canada | F1240: James Brown | G1240: Product B | H1240: 11 | I1240: 321 | J1240: 80250 | K1240: 9630
A1241: 11240 | B1241: =YEAR(C1241) -> 2022 | C1241: 44682 | D1241: =D1240+1 -> 44705 | E1241: New Zealand | F1241: Emily White | G1241: Product C | H1241: 22 | I1241: 247 | J1241: 86450 | K1241: 26799.5
A1242: 11241 | B1242: =YEAR(C1242) -> 2022 | C1242: 44682 | D1242: =D1241+1 -> 44706 | E1242: UK | F1242: John Smith | G1242: Product C | H1242: 27 | I1242: 489 | J1242: 171150 | K1242: 18826.5
A1243: 11242 | B1243: =YEAR(C1243) -> 2022 | C1243: 44682 | D1243: =D1242+1 -> 44707 | E1243: UK | F1243: John Smith | G1243: Product B | H1243: 12 | I1243: 214 | J1243: 53500 | K1243: 7490
A1244: 11243 | B1244: =YEAR(C1244) -> 2022 | C1244: 44682 | D1244: =D1243+1 -> 44708 | E1244: USA | F1244: John Smith | G1244: Product B | H1244: 5 | I1244: 269 | J1244: 67250 | K1244: 8742.5
A1245: 11244 | B1245: =YEAR(C1245) -> 2022 | C1245: 44682 | D1245: =D1244+1 -> 44709 | E1245: Canada | F1245: James Brown | G1245: Product B | H1245: 30 | I1245: 491 | J1245: 122750 | K1245: 33142.5
A1246: 11245 | B1246: =YEAR(C1246) -> 2022 | C1246: 44682 | D1246: =D1245+1 -> 44710 | E1246: Australia | F1246: James Brown | G1246: Product C | H1246: 13 | I1246: 289 | J1246: 101150 | K1246: 15172.5
A1247: 11246 | B1247: =YEAR(C1247) -> 2022 | C1247: 44682 | D1247: =D1246+1 -> 44711 | E1247: New Zealand | F1247: James Brown | G1247: Product C | H1247: 2 | I1247: 58 | J1247: 20300 | K1247: 5887
... A1462: 11461 | B1462: =YEAR(C1462) -> 2022 | C1462: 44896 | D1462: =D1461+1 -> 44926 | E1462: Canada | F1462: Emily White | G1462: Product D | H1462: 1 | I1462: 50 | J1462: 42500 | K1462: 18275
